{
  "version": "1.1.0",
  "windows": {
    "main": {
      "layout": {
        "children": [
          {
            "children": [
              {
                "active": 0,
                "children": [
                  "hierarchy"
                ],
                "height": 434,
                "type": "panel",
                "width": 278
              },
              {
                "active": 0,
                "children": [
                  "assets"
                ],
                "height": 373,
                "type": "panel",
                "width": 278
              }
            ],
            "height": 810,
            "type": "dock-v",
            "width": 278
          },
          {
            "children": [
              {
                "children": [
                  {
                    "active": 0,
                    "children": [
                      "scene"
                    ],
                    "height": 500,
                    "type": "panel",
                    "width": 402
                  },
                  {
                    "active": 0,
                    "children": [
                      "node-library"
                    ],
                    "height": 500,
                    "type": "panel",
                    "width": 200
                  }
                ],
                "height": 500,
                "type": "dock-h",
                "width": 605
              },
              {
                "active": 0,
                "children": [
                  "console",
                  "timeline"
                ],
                "height": 307,
                "type": "panel",
                "width": 605
              }
            ],
            "height": 810,
            "type": "dock-v",
            "width": 605
          },
          {
            "active": 0,
            "children": [
              "inspector"
            ],
            "height": 810,
            "type": "panel",
            "width": 512
          }
        ],
        "snapshot": true,
        "type": "dock-h"
      },
      "x": 419,
      "y": 67,
      "width": 1423,
      "height": 939
    }
  }
}